chatsnack/__init__.py
chatsnack/aiclient.py
chatsnack/asynchelpers.py
chatsnack/chat/__init__.py
chatsnack/chat/mixin_messages.py
chatsnack/chat/mixin_params.py
chatsnack/chat/mixin_query.py
chatsnack/chat/mixin_serialization.py
chatsnack/chat/mixin_utensil.py
chatsnack/defaults.py
chatsnack/fillings.py
chatsnack/packs/__init__.py
chatsnack/packs/default_packs/ChatsnackHelper.yml
chatsnack/packs/default_packs/Chester.yml
chatsnack/packs/default_packs/Confectioner.yml
chatsnack/packs/default_packs/Data.yml
chatsnack/packs/default_packs/Jane.yml
chatsnack/packs/default_packs/Jolly.yml
chatsnack/packs/default_packs/Summarizer.yml
chatsnack/packs/module_help_vendor.py
chatsnack/packs/snackpacks.py
chatsnack/patches/__init__.py
chatsnack/patches/patch_datafiles.py
chatsnack/txtformat.py
chatsnack/utensil.py
chatsnack/yamlformat.py
chatsnack-0.4.5.dist-info/LICENSE
chatsnack-0.4.5.dist-info/METADATA
chatsnack-0.4.5.dist-info/WHEEL
chatsnack-0.4.5.dist-info/RECORD
