Metadata-Version: 2.1
Name: chatsnack
Version: 0.4.5
Summary: chatsnack is the easiest Python library for rapid development with OpenAI's ChatGPT API. It provides an intuitive interface for creating and managing chat-based prompts and responses, making it convenient to build complex, interactive conversations with AI.
License: MIT
Author: Mattie Casper
Requires-Python: >=3.10,<4.0
Classifier: License :: OSI Approved :: MIT License
Classifier: Programming Language :: Python :: 3
Classifier: Programming Language :: Python :: 3.10
Classifier: Programming Language :: Python :: 3.11
Provides-Extra: examples
Provides-Extra: flask
Provides-Extra: questionary
Provides-Extra: rich
Requires-Dist: Flask (>=2.1,<3.0) ; extra == "flask" or extra == "examples"
Requires-Dist: datafiles (>=2.0,<3.0)
Requires-Dist: loguru (>=0.6.0,<0.7.0)
Requires-Dist: nest-asyncio (>=1.5.6,<2.0.0)
Requires-Dist: openai (>=1.2.4,<2.0.0)
Requires-Dist: python-dotenv (>=1.0.0,<2.0.0)
Requires-Dist: questionary (>=1.10.0,<2.0.0) ; extra == "questionary" or extra == "examples"
Requires-Dist: rich (>=13.3.2,<14.0.0) ; extra == "rich" or extra == "examples"
